dephell_licenses-0.1.7.dist-info/dependency_links.txt
dephell_licenses-0.1.7.dist-info/entry_points.txt
dephell_licenses-0.1.7.dist-info/METADATA
dephell_licenses-0.1.7.dist-info/top_level.txt
dephell_licenses-0.1.7.dist-info/WHEEL
dephell_licenses/_cached_property.py
dephell_licenses/_license.py
dephell_licenses/_licenses.py
dephell_licenses/__init__.py
dephell_licenses/licenses.json
dephell_licenses-0.1.7.dist-info/LICENSE
dephell_licenses-0.1.7.dist-info/RECORD