Metadata-Version: 2.1
Name: dephell-licenses
Version: 0.1.7
Summary: Get info about OSS licenses
Project-URL: Repository, https://github.com/dephell/dephell_licenses
Author: Gram
Author-email: gram@orsinium.dev
License: MIT
Requires-Python: >=3.5
Keywords: dephell,packaging,licenses,pypi
Classifier: Development Status :: 4 - Beta
Classifier: Intended Audience :: Developers
Classifier: License :: OSI Approved :: MIT License
Classifier: Programming Language :: Python
Classifier: Topic :: Software Development :: Libraries :: Python Modules
Classifier: Programming Language :: Python :: 3.5
Classifier: Programming Language :: Python :: 3.6
Classifier: Programming Language :: Python :: 3.7
Classifier: Programming Language :: Python :: 3.8
Classifier: Programming Language :: Python :: Implementation :: CPython
Classifier: Programming Language :: Python :: Implementation :: PyPy
Classifier: Operating System :: MacOS
Classifier: Operating System :: Microsoft :: Windows
Classifier: Operating System :: Unix
Requires-Dist: attrs
Requires-Dist: requests
